pymsgbboxexmaple10525.py
pymsgbboxexmaple10525-0.1.0.dist-info/METADATA
pymsgbboxexmaple10525-0.1.0.dist-info/WHEEL
pymsgbboxexmaple10525-0.1.0.dist-info/RECORD
