Metadata-Version: 2.1
Name: pymsgbboxexmaple10525
Version: 0.1.0
Summary: Hello test ptoject
Author: Karolina
Author-email: you@example.com
Requires-Python: >=3.11,<4.0
Classifier: Programming Language :: Python :: 3
Classifier: Programming Language :: Python :: 3.11
Classifier: Programming Language :: Python :: 3.12
Requires-Dist: pymsgbox (>=1.0.9,<2.0.0)
